{
    "book_title": "The Snowman's Winter Journey",
    "source_language": "en",
    "target_language": "vi",
    "total_pages": 8,
    "pages": [
        {
            "page_id": 1,
            "text_blocks": [
                {
                    "text": "It was a cold winter morning. Snow covered the entire village like a white blanket.",
                    "bbox": [50, 100, 500, 150],
                    "entities": [
                        {"name": "Snow", "type": "weather_entity"},
                        {"name": "Winter", "type": "weather_entity"},
                        {"name": "Village", "type": "location"}
                    ]
                },
                {
                    "text": "Little Anna put on her wool hat and warm coat before stepping outside.",
                    "bbox": [50, 160, 500, 210],
                    "entities": [
                        {"name": "Anna", "type": "character"},
                        {"name": "Wool Hat", "type": "clothing"},
                        {"name": "Warm Coat", "type": "clothing"}
                    ]
                }
            ]
        },
        {
            "page_id": 2,
            "text_blocks": [
                {
                    "text": "Anna and her brother Tom ran to the fireplace to warm up after playing in the snow.",
                    "bbox": [50, 100, 500, 150],
                    "entities": [
                        {"name": "Anna", "type": "character"},
                        {"name": "Tom", "type": "character"},
                        {"name": "Fireplace", "type": "object"},
                        {"name": "Snow", "type": "weather_entity"}
                    ]
                },
                {
                    "text": "Their grandmother made hot chocolate with marshmallows by the fireplace.",
                    "bbox": [50, 160, 500, 210],
                    "entities": [
                        {"name": "Grandmother", "type": "character"},
                        {"name": "Hot Chocolate", "type": "food"},
                        {"name": "Fireplace", "type": "object"}
                    ]
                }
            ]
        },
        {
            "page_id": 3,
            "text_blocks": [
                {
                    "text": "The children built a Snowman in the garden. They used a carrot for his nose.",
                    "bbox": [50, 100, 500, 150],
                    "entities": [
                        {"name": "Snowman", "type": "character"},
                        {"name": "Carrot", "type": "object"},
                        {"name": "Snow", "type": "weather_entity"}
                    ]
                },
                {
                    "text": "Anna gave the Snowman her old wool hat to keep him warm.",
                    "bbox": [50, 160, 500, 210],
                    "entities": [
                        {"name": "Anna", "type": "character"},
                        {"name": "Snowman", "type": "character"},
                        {"name": "Wool Hat", "type": "clothing"}
                    ]
                }
            ]
        },
        {
            "page_id": 4,
            "text_blocks": [
                {
                    "text": "That night, the Snowman came alive under the bright moonlight.",
                    "bbox": [50, 100, 500, 150],
                    "entities": [
                        {"name": "Snowman", "type": "character"},
                        {"name": "Moonlight", "type": "weather_entity"}
                    ]
                },
                {
                    "text": "The Snowman took Anna on a magical sleigh ride through the winter forest.",
                    "bbox": [50, 160, 500, 210],
                    "entities": [
                        {"name": "Snowman", "type": "character"},
                        {"name": "Anna", "type": "character"},
                        {"name": "Sleigh", "type": "vehicle"},
                        {"name": "Winter", "type": "weather_entity"},
                        {"name": "Forest", "type": "location"}
                    ]
                }
            ]
        },
        {
            "page_id": 5,
            "text_blocks": [
                {
                    "text": "They flew over the snowy mountains and saw the Northern Lights dancing in the sky.",
                    "bbox": [50, 100, 500, 150],
                    "entities": [
                        {"name": "Snow", "type": "weather_entity"},
                        {"name": "Northern Lights", "type": "weather_entity"},
                        {"name": "Mountains", "type": "location"}
                    ]
                },
                {
                    "text": "The Snowman showed Anna the ice palace where the Snow Queen lived.",
                    "bbox": [50, 160, 500, 210],
                    "entities": [
                        {"name": "Snowman", "type": "character"},
                        {"name": "Anna", "type": "character"},
                        {"name": "Ice Palace", "type": "location"},
                        {"name": "Snow Queen", "type": "character"}
                    ]
                }
            ]
        },
        {
            "page_id": 6,
            "text_blocks": [
                {
                    "text": "The Snow Queen gave Anna a magical ice crystal that would never melt.",
                    "bbox": [50, 100, 500, 150],
                    "entities": [
                        {"name": "Snow Queen", "type": "character"},
                        {"name": "Anna", "type": "character"},
                        {"name": "Ice Crystal", "type": "object"}
                    ]
                },
                {
                    "text": "Winter is the most magical season, the Snow Queen said with a gentle smile.",
                    "bbox": [50, 160, 500, 210],
                    "entities": [
                        {"name": "Winter", "type": "weather_entity"},
                        {"name": "Snow Queen", "type": "character"}
                    ]
                }
            ]
        },
        {
            "page_id": 7,
            "text_blocks": [
                {
                    "text": "As the sun rose, the Snowman began to melt. Anna held his carrot nose and cried.",
                    "bbox": [50, 100, 500, 150],
                    "entities": [
                        {"name": "Snowman", "type": "character"},
                        {"name": "Anna", "type": "character"},
                        {"name": "Carrot", "type": "object"}
                    ]
                },
                {
                    "text": "Tom found Anna sitting by the fireplace, holding the carrot and the wool hat.",
                    "bbox": [50, 160, 500, 210],
                    "entities": [
                        {"name": "Tom", "type": "character"},
                        {"name": "Anna", "type": "character"},
                        {"name": "Fireplace", "type": "object"},
                        {"name": "Carrot", "type": "object"},
                        {"name": "Wool Hat", "type": "clothing"}
                    ]
                }
            ]
        },
        {
            "page_id": 8,
            "text_blocks": [
                {
                    "text": "Anna smiled and looked at the ice crystal. It sparkled like the snow outside.",
                    "bbox": [50, 100, 500, 150],
                    "entities": [
                        {"name": "Anna", "type": "character"},
                        {"name": "Ice Crystal", "type": "object"},
                        {"name": "Snow", "type": "weather_entity"}
                    ]
                },
                {
                    "text": "Next winter, I will build another Snowman, Anna whispered. And we will fly again.",
                    "bbox": [50, 160, 500, 210],
                    "entities": [
                        {"name": "Winter", "type": "weather_entity"},
                        {"name": "Snowman", "type": "character"},
                        {"name": "Anna", "type": "character"}
                    ]
                }
            ]
        }
    ]
}
